luadata/luatable/__init__.py
luadata_luatable-0.0.3.dist-info/LICENSE
luadata_luatable-0.0.3.dist-info/METADATA
luadata_luatable-0.0.3.dist-info/WHEEL
luadata_luatable-0.0.3.dist-info/top_level.txt
luadata_luatable-0.0.3.dist-info/RECORD
